{
  "id": "naxos-rock",
  "title": "Live A Little",
  "subtitle": "Naxos, Greece — May 2024",
  "description": "Jace on a perfectly placed rock in Naxos, suspended inside the stillness that later became his poem Live a Little.",
  "source": {
    "type": "instagram-carousel",
    "photo": "photo.jpg",
    "depth": null,
    "mask": null,
    "generator": "world-model",
    "generated": "2026-03-26",
    "postDate": "May 08, 2024 6:52 am",
    "worldModelPrompt": "Wide Mediterranean shoreline memory in Naxos, Greece at golden hour. Preserve the original seated boy on the foreground rock in a bright blue hoodie as the clear focal human anchor. Reconstruct the surrounding granite rock field, shallow tide pool, ocean horizon, islands, and sky as a cohesive fully explorable 360 coastal world. Keep the seated boy readable and intact, preserve ground continuity around him, avoid floating fragments or detached blocks, and complete the unseen environment with believable rock formations, sand, tide pools, and Aegean light.",
    "postImages": [
      "/images/Instagram/media/posts/202405/18011396732371399.jpg",
      "/images/Instagram/media/posts/202405/18033946798786712.jpg",
      "/images/Instagram/media/posts/202405/17917063217823264.jpg",
      "/images/Instagram/media/posts/202405/18122780437357613.jpg"
    ],
    "generationMode": "single-image-world-model",
    "expansion": {
      "strategy": "learned-scene-expansion",
      "stage": "world-model-fused",
      "bundle": "world/view-bundle.json",
      "sourceViewCount": 1,
      "generatedViewCount": 0,
      "totalViewCount": 1,
      "anchorGenerator": "source-photo",
      "viewSynthesizer": "world-model",
      "fusionEngine": "world-model",
      "compositeViewCount": 1
    }
  },
  "world": {
    "splat": "world/scene.runtime.ply",
    "sourceSplat": "world/scene.ply",
    "mesh": null,
    "collider": null,
    "format": "ply",
    "splatCount": 850000,
    "sourceSplatCount": 16515072,
    "bounds": null,
    "transform": {
      "position": [
        0,
        0,
        0
      ],
      "scale": [
        1,
        1,
        1
      ],
      "rotation": [
        1,
        0,
        0,
        0
      ]
    },
    "provenance": {
      "tier": "world-model-fused",
      "anchorGenerator": "source-photo",
      "reconstruction": "single-image-world-model",
      "viewCount": 1
    }
  },
  "fallback": {
    "type": "photo-preview",
    "photo": "photo.jpg"
  },
  "camera": {
    "startPosition": [
      0.24,
      0.12,
      5.8
    ],
    "startTarget": [
      0,
      0.03,
      0
    ],
    "fov": 52,
    "near": 0.1,
    "far": 80
  },
  "narrative": [
    {
      "threshold": 0.18,
      "text": "A boy sits on a perfectly placed rock in a perfectly placed world."
    },
    {
      "threshold": 0.48,
      "text": "The sea keeps moving. He stays still long enough for the whole shore to sound like a thought."
    },
    {
      "threshold": 0.8,
      "text": "Sometimes a life changes because someone finally decides to live a little."
    }
  ],
  "soundscape": {
    "layers": []
  },
  "transitions": {
    "next": "naxos-laugh",
    "previous": "syros-cave",
    "anchors": []
  }
}
